{
  "FMM" : {
    "schoolhead": [
      "School Head",
      "SR. Teresita P. Elevera FMM",
      "http://stellamariscollegeqc.edu.ph/wp-content/uploads/2021/04/srtess.jpg",
      "nextRow"
    ]
    ,
    "financeOfficer": [
      "Finance Officer",
      "SR. AMELITA T. ABALOS FMM",
      "http://stellamariscollegeqc.edu.ph/wp-content/uploads/2021/04/sramy.jpg",
      ""
    ],
    "wellBeing": [
      "Student Well-being",
      "SR. MARY CONCEPCION T. JOMEN FMM",
      "http://stellamariscollegeqc.edu.ph/wp-content/uploads/2021/05/srsiony.jpg",
      ""
    ],
    "canteenSupervisor": [
      "Canteen Supervisor",
      "SR. ERLINDA  STA. ROMANA FMM",
      "http://stellamariscollegeqc.edu.ph/wp-content/uploads/2021/05/srerlinda.jpg",
      ""
    ]
  },
  "SALT": {
    "AralingPanlipunan": [
      "Araling Panlipunan",
      "Mrs. Edna B. Oxales ",
      "http://stellamariscollegeqc.edu.ph/wp-content/uploads/2021/03/199606001-1.jpg",
      ""
    ],
    "CLE": [
      "Christian Life Education",
      "Mr. Rengin M. Fabula ",
      "http://stellamariscollegeqc.edu.ph/wp-content/uploads/2021/03/200106001-1.jpg",
      ""
    ],
    "Filipino": [
      "Filipino",
      "Mrs. Chryzl Anne A. Gallardo ",
      "http://stellamariscollegeqc.edu.ph/wp-content/uploads/2021/03/201406001-1.jpg",
      "nextRow"
    ],
    "Mathematics": [
      "Mathematics",
      "Ms. Marife O. Corpuz ",
      "http://stellamariscollegeqc.edu.ph/wp-content/uploads/2021/03/201006001-1.jpg",
      ""
    ],
    "MAPEH": [
      "MAPEH",
      "Ms. Cherry Rose C. Mendoza ",
      "http://stellamariscollegeqc.edu.ph/wp-content/uploads/2021/03/201706004.jpg",
      ""
    ],
    "Science": [
      "Science",
      "Mrs. Lusita B. Sabalburo ",
      "http://stellamariscollegeqc.edu.ph/wp-content/uploads/2021/03/199006002.jpg",
      ""
    ],
    "TLEICT": [
      "TLE / ICT",
      "Ms. Marie Paz Claire S. Gallardo ",
      "http://stellamariscollegeqc.edu.ph/wp-content/uploads/2021/03/200106002.jpg",
      ""
    ]
  },
  "DepartmentHeads": {
    "AcademicChair": [
      "Academic Chair",
      "Mrs. Edna B. Oxales ",
      "http://stellamariscollegeqc.edu.ph/wp-content/uploads/2021/03/199606001-1.jpg",
      ""
    ],
    "GuidanceChair": [
      "Guidance Chair",
      "Ms. Nila  Castro ",
      "http://stellamariscollegeqc.edu.ph/wp-content/uploads/2021/03/200306001.jpg",
      ""
    ],
    "OSAChair": [
      "OSA Chair",
      "Mr. Alejo Leobort M. Coronel ",
      "http://stellamariscollegeqc.edu.ph/wp-content/uploads/2021/03/201206002.jpg",
      "nextRow"
    ],
    "HRO": [
      "Human Resource Officer",
      "Ms. Frcille T. Jongco ",
      "http://stellamariscollegeqc.edu.ph/wp-content/uploads/2021/03/200511001.jpg",
      ""
    ],
    "Registrar": [
      "Registrar",
      "Ms. Jeniffer B. Martin ",
      "http://stellamariscollegeqc.edu.ph/wp-content/uploads/2021/03/199805001.jpg",
      ""
    ],
    "AccountingHead": [
      "Accounting Head",
      "Ms. Marichel M. Mateo ",
      "http://stellamariscollegeqc.edu.ph/wp-content/uploads/2021/03/201505001.jpg",
      ""
    ]
  }
}